django_hacs-1.0a2.dist-info/WHEEL
django_hacs-1.0a2.dist-info/RECORD
django_hacs-1.0a2.dist-info/top_level.txt
django_hacs-1.0a2.dist-info/metadata.json
django_hacs-1.0a2.dist-info/METADATA
django_hacs-1.0a2.dist-info/DESCRIPTION.rst
hacs/utils.py
hacs/admin.py
hacs/django_utils_version.py
hacs/fields.py
hacs/models.py
hacs/middleware.py
hacs/apps.py
hacs/urls.py
hacs/__init__.py
hacs/globals.py
hacs/defaults.py
hacs/lru_wrapped.py
hacs/locales/.gitkeep
hacs/views/errors.py
hacs/views/__init__.py
hacs/views/__pycache__/__init__.cpython-34.pyc
hacs/generated/.gitignore
hacs/management/__init__.py
hacs/management/commands/import_routes.py
hacs/management/commands/init_hacs.py
hacs/management/commands/__init__.py
hacs/management/commands/export_routes.py
hacs/management/commands/__pycache__/__init__.cpython-34.pyc
hacs/management/commands/__pycache__/export_routes.cpython-34.pyc
hacs/management/commands/__pycache__/import_routes.cpython-34.pyc
hacs/management/commands/__pycache__/init_hacs.cpython-34.pyc
hacs/management/__pycache__/__init__.cpython-34.pyc
hacs/__pycache__/utils.cpython-34.pyc
hacs/__pycache__/urls.cpython-34.pyc
hacs/__pycache__/defaults.cpython-34.pyc
hacs/__pycache__/admin.cpython-34.pyc
hacs/__pycache__/lru_wrapped.cpython-34.pyc
hacs/__pycache__/__init__.cpython-34.pyc
hacs/__pycache__/apps.cpython-34.pyc
hacs/__pycache__/models.cpython-34.pyc
hacs/__pycache__/fields.cpython-34.pyc
hacs/__pycache__/globals.cpython-34.pyc
hacs/__pycache__/middleware.cpython-34.pyc
hacs/__pycache__/django_utils_version.cpython-34.pyc
hacs/migrations/__init__.py
hacs/migrations/0001_initial.py
hacs/migrations/__pycache__/0001_initial.cpython-34.pyc
hacs/migrations/__pycache__/__init__.cpython-34.pyc
