Metadata-Version: 2.0
Name: django-hacs
Version: 1.0a2
Summary: Hybrid Access Control System for Django
Home-page: https://pypi.python.org/pypi/django-hacs
Author: Md Nazrul Islam
Author-email: email2nazrul@gmail.com
License: GPL version 3
Keywords: Python Django ACL ACS IAM Security Authentication Authorization
Platform: UNKNOWN
Classifier: Development Status :: 3 - Alpha
Classifier: Environment :: Web Environment
Classifier: Framework :: Django
Classifier: Intended Audience :: Developers
Classifier: License :: OSI Approved :: GNU Lesser General Public License v3 (LGPLv3)
Classifier: Operating System :: OS Independent
Classifier: Programming Language :: Python
Classifier: Programming Language :: Python :: 2
Classifier: Programming Language :: Python :: 2.7
Classifier: Programming Language :: Python :: 3
Classifier: Programming Language :: Python :: 3.4
Classifier: Programming Language :: Python :: 3.5
Classifier: Topic :: Internet :: WWW/HTTP
Classifier: Topic :: Internet :: WWW/HTTP :: Dynamic Content
Classifier: Topic :: Internet :: WWW/HTTP :: WSGI
Classifier: Topic :: Software Development :: Libraries :: Application Frameworks
Classifier: Topic :: Software Development :: Libraries :: Python Modules
Requires-Dist: django
Provides-Extra: test
Requires-Dist: pytest; extra == 'test'
Requires-Dist: pytest-django; extra == 'test'
